delegation/__init__.py
delegation/admin.py
delegation/apps.py
delegation/authentication.py
delegation/models.py
delegation/permissions.py
delegation/serializers.py
delegation/tests.py
delegation/urls.py
delegation/views.py
delegation/migrations/0001_initial.py
delegation/migrations/__init__.py
django_delegate_access-0.0.1.dist-info/METADATA
django_delegate_access-0.0.1.dist-info/WHEEL
django_delegate_access-0.0.1.dist-info/top_level.txt
django_delegate_access-0.0.1.dist-info/RECORD
